nginqcomm
