Metadata-Version: 2.1
Name: nginqcomm
Version: 0.2.14
Summary: nginq common lib
Home-page: https://git.pandaminer.com/quant/nginq-common
Author: zhoushx1018
Author-email: zhoushx1018@gmail.com
License: MIT
Platform: UNKNOWN
Classifier: License :: OSI Approved :: MIT License
Classifier: Programming Language :: Python
Classifier: Programming Language :: Python :: 3
Classifier: Programming Language :: Python :: 3.6
Classifier: Programming Language :: Python :: Implementation :: CPython
Classifier: Programming Language :: Python :: Implementation :: PyPy
Requires-Python: >=3.9.0
License-File: LICENSE
